ray_sqlalchemy/__init__.py
ray_sqlalchemy/all.py
ray_sqlalchemy-0.0.2.dist-info/DESCRIPTION.rst
ray_sqlalchemy-0.0.2.dist-info/METADATA
ray_sqlalchemy-0.0.2.dist-info/RECORD
ray_sqlalchemy-0.0.2.dist-info/WHEEL
ray_sqlalchemy-0.0.2.dist-info/metadata.json
ray_sqlalchemy-0.0.2.dist-info/top_level.txt
