Metadata-Version: 2.0
Name: ray-sqlalchemy
Version: 0.0.2
Summary: UNKNOWN
Home-page: http://github.com/felipevolpone/ray
Author: Felipe Volpone
Author-email: felipevolpone@gmail.com
License: MIT
Keywords: python framework ray api rest
Platform: UNKNOWN
Classifier: Development Status :: 3 - Alpha
Classifier: Topic :: Utilities
Requires-Dist: sqlalchemy
